{
  "lang": "ru",
  "ignoreUrls": true,
  "ignoreText": [
    "(\\d+|n)-(го|е|й|м|ми|му|х|ю|я)",
    ""
  ],
  "excludeFiles": [
    "[.].*",
    "dist/**/*",
    "node_modules/**/*",
    "src/api/**/*",
    "src/assets/**/*",
    "src/config/**/*",
    "src/fonts/**/*",
    "src/images/**/*",
    "src/includes/**/*",
    "src/layouts/**/*",
    "src/scripts/**/*",
    "src/styles/**/*"
  ],
  "checkYo": true,
  "dictionary": [
    "[0-9]+[A-Za-zА-Яа-я]",
    "(P|р)епост(ы|)",
    "(R|r)equest'(а|ов)",
    "(R|r)equest",
    "(А|а)кадем",
    "(А|а)мбассадор(а|ами|ов|ства|ы|)",
    "(А|В)[1-4]",
    "(В|в)окальн(о|)",
    "(В|в)олонтёр(а|ам|ами|ов|ские|ский|ских|ского|ское|ской|ства|стве|у|ы|)",
    "(В|в)оркшоп(а|е|ов|ы|)",
    "(Г|г)лавред(у|)",
    "(Г|г)угл",
    "(И|и)вент(а|)",
    "(И|и)нфокоммуникационные",
    "(К|к)иберспортивн(ое|ой|ой|ом|ому|ую|ый|ый|ым)",
    "(К|к)одить",
    "(К|к)оллайдер(а|е|)",
    "(Л|л)азертаг(а|у|)",
    "(Л|л)айфхак(ами|ах|)",
    "(М|м)етаматериал(ам|ы|)",
    "(М|м)икросервис(ам|ная|ов|ы|)",
    "(М|м)итап(а|ах|е|)",
    "(П|п)ервак(а|ов|)",
    "(П|п)ромокод(у|ы|)",
    "(С|с)витшот(а|ы|)",
    "(С|с)лэм(е|еров|)",
    "(С|с)пециалитет(а|)",
    "(С|с)пинтроника",
    "(С|с)трайкбольная",
    "(С|с)трессоустойчивость",
    "(Т|т)елеграм(е|)",
    "(Т|т)ермокружк(а|и)",
    "(Т|т)онкопленочны(е|х)",
    "(Х|х)акатон(а|ах|е|ов|ы|)",
    "(Э|э)ндаумент",
    "3х4",
    "4x100м",
    "Aкад",
    "BIOS(а|е)",
    "CAПР",
    "Cенсорные",
    "DataArtпровела",
    "Dаnоnе",
    "Escapе",
    "Exeс",
    "Frontеnd",
    "HR'ы",
    "IIой",
    "IQмористической",
    "IТ",
    "Javasсript",
    "PROVOКАЦИЯ",
    "proБЮДЖЕТ",
    "REAльные",
    "А3В5",
    "Аалто",
    "Авакян",
    "автоматизатор(а|ов|)",
    "автотестов",
    "Автроы",
    "Агиар",
    "агроуниверситета",
    "Адемар",
    "АЕДОН",
    "АИС",
    "айтишник(а|и|)",
    "актово",
    "акустооптоэлектроники",
    "Алабуга",
    "Алгазинов",
    "Алейникова",
    "Алмалиев",
    "Алфёровск(ая|ий|ой|ого|ую|)",
    "Альпинстудия",
    "американо",
    "Аникандрова",
    "Антиплагиат",
    "Антоканова",
    "АСНИ",
    "ассертивность",
    "АССК",
    "Астанову",
    "Атомтехэнерго",
    "Атомэнергоремонт",
    "ауд",
    "Аушвиц",
    "ачивки",
    "Ашкин",
    "Афроевразийская",
    "Аэдон",
    "Аэроквантум",
    "баг(ах|ов|)",
    "Базюра",
    "Байбуз",
    "Баларда",
    "Баларт",
    "банкинг",
    "Баркаловой",
    "Батанина",
    "Баткина",
    "батл(а|)",
    "Батраченко",
    "БАХ(а|у|)",
    "Баца",
    "БГУ",
    "бейджей",
    "бекенд",
    "Белобродский",
    "Белоконевым",
    "Бернгард",
    "Бесединой",
    "БессмертныйПолк",
    "БиКМОП",
    "биоинформатика",
    "биомониторинг",
    "биофотоник(а|и|е)",
    "Бирин",
    "БиТ",
    "Биткойн",
    "Битрикс24",
    "блокчейне",
    "Бобрешов",
    "Бобрешова",
    "Бобрешову",
    "Боганец",
    "Богацкая",
    "боксерские",
    "Болдинова",
    "Бормонтов",
    "Боровлева",
    "Борсякова",
    "БПЛА",
    "бразерс",
    "Бразерс",
    "Бранд(а|)",
    "Бреев",
    "Брееву",
    "брейкпоинтов",
    "брендированная",
    "Бузов",
    "Буйлов(у|)",
    "Булеков",
    "Бухвалов(а|ой)",
    "Бухтаева",
    "БФТ",
    "БЦ",
    "БЦХ",
    "бьюти",
    "бэкенд(а|ом|)",
    "бэнда",
    "Бэриш",
    "Бэти",
    "Вак",
    "Варгач",
    "Вахтель",
    "ВВА",
    "ВГИФК",
    "ВГЛТУ",
    "ВГМУ",
    "ВГТУ",
    "вгу",
    "ВГУ",
    "ВГУИТ",
    "вгукоронныйвыпуск",
    "Вейцзекер",
    "Величкина",
    "Величкину",
    "Велогород",
    "велозабег",
    "велоколонны",
    "Веневитино",
    "Веневитиново",
    "Верберком",
    "Веремеенко",
    "Веремьева",
    "версионирование",
    "верстки",
    "взаиморасчетам",
    "ВЗПП",
    "Видеоконтент",
    "видеолекци(и|ям)",
    "видеомост",
    "видеообращения",
    "виджето(в|м)",
    "Виневитино",
    "ВКонакте",
    "ВКонаткте",
    "Вконтакте",
    "ВКонтакте",
    "ВКР",
    "ВНИИФ",
    "ВНИМАНИ",
    "Воевудский",
    "Воищев",
    "Воищеву",
    "Воронежсельмаш",
    "ВП",
    "ВСК",
    "ВСТФ",
    "ВТБ",
    "ВТЮФ",
    "ВЦКБ",
    "ВШЭ",
    "выХод",
    "Вэй",
    "газочувствительных",
    "Газпромбанк(а|)",
    "Галичья",
    "Гарифуллина",
    "Гарнизонокосильщик",
    "ГБУ",
    "ГГиТ",
    "геймдеве",
    "Геманией",
    "гетероконтакта",
    "гетеропар",
    "гетерослоем",
    "гетрогенных",
    "Геттингемском",
    "ГИА",
    "Гилёва",
    "Гилёвой",
    "гифке",
    "Гликлих",
    "ГЛОНАСС",
    "Гогаладзе",
    "Голев",
    "Головацк(ая|ой)",
    "госзакупок",
    "госпедуниверситета",
    "ГостевойПост",
    "Госуслугам",
    "Госуслуги",
    "Гревцева",
    "Гревцевой",
    "Грув",
    "Грудинину",
    "Грэйд",
    "Гудинаф",
    "Гульк",
    "Гутенберга",
    "Дашевский",
    "дд",
    "дд",
    "Дебликов",
    "девайсов",
    "девелоп",
    "Деграсса",
    "Дегтярь",
    "Дедяев",
    "денормализации",
    "ДеньКосмонавтики",
    "Деревянко",
    "Дерепко",
    "дерных",
    "десктопных",
    "Дехаева",
    "деятельнос",
    "Джорджема",
    "джуниорами",
    "джунов",
    "Диас",
    "дизайнерства",
    "дикректор",
    "дирижера",
    "Дмитри",
    "ДоброСвет",
    "договоренности",
    "Домашевск(ая|ой|ую)",
    "домашек",
    "Донако",
    "Доностиа",
    "Доппел(ь|ю|я)",
    "ДПО",
    "Дрождин",
    "дронов",
    "дудл",
    "ДЭГ",
    "евроинтеграции",
    "Егорушина",
    "Емкость",
    "Ендовицкий",
    "Ендовицкого",
    "ЕСКД",
    "Желтый",
    "Жукалина",
    "ЖурФака",
    "ЖурФаком",
    "Забровская",
    "Задеба",
    "Залукаевым",
    "запоминалки",
    "Запрягаева",
    "зарубеж",
    "заставочками",
    "Зафран",
    "Зволле",
    "Зеленского",
    "Зеленый",
    "знаетъ",
    "Золотерев",
    "ЗП",
    "Зубанков",
    "Зубанкову",
    "Зулейха",
    "ИБ",
    "Игросфер(а|у|ы)",
    "Игротехник",
    "Иконин",
    "имплантантов",
    "импортозамещени(и|я)",
    "инбокса",
    "ИндиGo",
    "инноваторам",
    "инновационно",
    "Иннополис",
    "ИнноЦентр",
    "ИНОБИТЕК",
    "инсектариума",
    "Интерскол",
    "Интерстеллар",
    "Интехрос",
    "Инфо(Т|т)ех",
    "инфографика",
    "Инфоком",
    "Информсвязь",
    "ИПФХ",
    "ИРЭ",
    "ИстФак",
    "ИТМО",
    "ИТЭБ",
    "ИЦАЭ",
    "кавер",
    "Кавецкий",
    "Кадменский",
    "КАДМЕНСКИЙ",
    "Кадменского",
    "Казанчян",
    "Какулия",
    "Калтеха",
    "Камелот",
    "кампусной",
    "Капшуков",
    "Каркортской",
    "Карутина",
    "Катасонов",
    "Кахидзе",
    "Кашеверов",
    "квадрокоптер",
    "квазидетерминированных",
    "квазирадиосигнал(а|ов|)",
    "Кванториум(е|)",
    "квантум(а|)",
    "квиз(а|е|ы|)",
    "КГУ",
    "Кейна",
    "кейсовые",
    "КемГУ",
    "Кенигсон",
    "Кенигсоном",
    "Керсновский",
    "кибербезопасности",
    "киберграмотности",
    "киберклуб",
    "киберспорт(е|и|)",
    "киберспортивн(ого|ное|ной|ной|ном|ному|ную|ны|ный|ный|ным)",
    "киберспортсмен(ов|ом)",
    "Кикеля",
    "киловольтного",
    "Кинобатл",
    "Кинобаттл",
    "кинопоказ",
    "Кинопоказ",
    "Клементьев(а|у|)",
    "книжецой",
    "КНУ",
    "КОВИД",
    "кодинга",
    "Козлобаев",
    "Козявин",
    "коммит(а|ам)",
    "коммуникабильность",
    "комьюнити",
    "Кондусов",
    "контейниризации",
    "Контемпорари",
    "Контесте",
    "конфайнмента",
    "конферанц",
    "КООС",
    "короновирусной",
    "Коротышева",
    "Корыстин",
    "Костёнки",
    "Костерлитц(а|)",
    "Костылев(а|е|)",
    "Косяковой",
    "котрибьюторам",
    "КОФ",
    "кофебрейк",
    "Коюд(а|е|у|ы)",
    "Крейн",
    "криптовалюте",
    "Кровь5",
    "Кройчик",
    "Крокс",
    "Крутских",
    "Крыловецкий",
    "КТРУ",
    "Ктулху",
    "КТЦ",
    "Кубанёва",
    "Куксенок",
    "Купрюшин",
    "Курдюмова",
    "Куцову",
    "Куцовым",
    "Кэмбриджского",
    "лаб(у|ы)",
    "Лабс",
    "Лавлинскому",
    "лайв",
    "лайк",
    "Ланжавен",
    "Лауе",
    "лаунж",
    "лауряты",
    "лендинге",
    "Леново",
    "лети(е|ю|я)",
    "ЛетоСПользой",
    "Лизюкова",
    "Лисициным",
    "Литрес",
    "Лобынцева",
    "Логус",
    "ЛС",
    "Луговской",
    "ЛЭТИ",
    "Любашевский",
    "Любашевского",
    "Любашевскому",
    "м2",
    "М2М",
    "Магдыч",
    "магистрантка",
    "Мади",
    "Макконехи",
    "малоатомных",
    "Мальковской",
    "Мармо",
    "Марриотт",
    "Масимум",
    "Маск",
    "Мастерс",
    "матан",
    "матмехе",
    "матмоделей",
    "МатФак",
    "Матфаком",
    "МатФаком",
    "матфизики",
    "Матьяс",
    "МБОУ",
    "МБФ",
    "МГТУ",
    "МГУП",
    "мегасайенс",
    "Мегасайенс",
    "МедиАктив",
    "Медиапоток",
    "медтехе",
    "Мелякова",
    "мем(ами|ах|ов)",
    "менти",
    "Менумеровой",
    "Меренкова",
    "Меркури",
    "мерч(а|)",
    "Месбауэра",
    "мессбауэровской",
    "Металлоинвест",
    "метанавыки",
    "Мешель",
    "МИБ",
    "Мизгулин",
    "Микродизайн",
    "микроменеджмента",
    "микроэлектронщик",
    "Милицкий",
    "Минпромторг",
    "Минпромторга",
    "Мирвольд",
    "Миропольская",
    "МИСиС",
    "МИТХТ",
    "Михальский",
    "Молгород(а|)",
    "МОЛГОРОД",
    "МолодежкаОНФ",
    "МолодёжкаОНФ",
    "Молоцкий",
    "Молправ",
    "мониторить",
    "Монэ",
    "Моргачева",
    "Моркотенко",
    "МояГлавнаяКнига",
    "МРСК",
    "мрт",
    "МУВИК",
    "Музер",
    "Музера",
    "Мултых",
    "мультиагентные",
    "мультивселенные",
    "мультизадачные",
    "мультиметрами",
    "мультиметров",
    "(М|м)ультипространство",
    "мультиязычные",
    "МФТИ",
    "МФУ",
    "МФЦ",
    "МыВместе",
    "нагрузочнго",
    "НАйТи",
    "Нанобарьер",
    "наноигл",
    "нанокластеров",
    "нанокомпозитов",
    "нанокристаллов",
    "наноматериала",
    "наноматериалов",
    "нанонитей",
    "наноплазмоники",
    "наноразмерных",
    "наносистем",
    "нанослоёв",
    "Нанофест",
    "нанофотонике",
    "наотдыхались",
    "НастолKings",
    "настолки",
    "наукограда",
    "наукоемкие",
    "наукоемких",
    "наукоемкого",
    "наукоемкой",
    "научпоп",
    "Нахмансон(е|)",
    "НДФЛ",
    "неарийцы",
    "Невес",
    "незащищённ(ости|ым|ых)",
    "НЕМТ",
    "нетворкинг",
    "Нетологии",
    "нефтянников",
    "НЗБ",
    "низкопроговых",
    "НИИЭТ",
    "Никипело",
    "Никипелов",
    "Никитинско",
    "никнейм",
    "НИУ",
    "НИЯУ",
    "НЛМК",
    "Нововоронежатомтехэнерго",
    "Нововоронежской",
    "Новолипецкий",
    "НовостиВГУ",
    "Новоусманскую",
    "НОиОК",
    "Нолан",
    "Нолана",
    "Ноланами",
    "Норсофт",
    "НПА",
    "НПР",
    "Образовача",
    "ов",
    "ОГЭ",
    "одногруппникам",
    "одногруппники",
    "одноранговыми",
    "оЖиви",
    "ОИЯИ",
    "Олим",
    "олимпиа",
    "Олимпик",
    "Олимпике",
    "ОМС",
    "онкобольны(м|х)",
    "ОНУ",
    "ОНФ",
    "ООП",
    "оптоинформатика",
    "оргвзнос",
    "ОСО",
    "ОСОШ",
    "Остек",
    "Осьмую",
    "Откликнутсья",
    "отргвзнос",
    "отчислительный",
    "Офисмаг",
    "ОЭЗ",
    "ОЭСЗ",
    "паблик(е|)",
    "Павельвева",
    "Павловнау",
    "палантир",
    "Пальчикова",
    "Панинский",
    "ПАО",
    "Папоровой",
    "Пахотина",
    "Пачевскому",
    "ПДД",
    "Переверзев",
    "Переверткина",
    "Перевёрткина",
    "Перевозниковой",
    "перевыпус(ка|тить)",
    "перезачёт",
    "Пересёлков",
    "ПерспективныйСтудент",
    "Перхоров",
    "Пигарева",
    "Пикулевская",
    "Пикус",
    "пин",
    "ПКС",
    "плаван",
    "плазмонике",
    "Платинум",
    "платников",
    "платфор",
    "Плехановская",
    "ПМИ",
    "ПММ",
    "пн",
    "Поатомная",
    "погранология",
    "Подгрузка",
    "Подлесновой",
    "подноминация",
    "Подробка",
    "пожелаетъ",
    "полимезоморфных",
    "полифилов",
    "поляритонны(е|х)",
    "посещёни",
    "постфукусимским",
    "Потуданского",
    "ППО",
    "практиканских",
    "предзаказ",
    "Придаченск(ая|ой)",
    "Прих",
    "провально",
    "продакт",
    "проджект",
    "прожестикулируем",
    "Прожженный",
    "промо",
    "ПромТИМ",
    "Протек",
    "Профстажировки",
    "псевдоброкеры",
    "ПТШ",
    "пулреквест(а|е|ов)",
    "Пустыльник",
    "пуше",
    "р-НЕМТ",
    "радиоконструкции",
    "радиофаке",
    "радиофотоник(а|е)",
    "РадиоФФ",
    "Райса",
    "Райффайзен",
    "Расхожев",
    "РГФ",
    "реалити",
    "Режепп",
    "рекрутеров",
    "Рексофт",
    "Релэкс",
    "РЕЛЭКС",
    "Репика",
    "Репосты",
    "Риа",
    "ридберговских",
    "РИНЦ",
    "РИФ(е|)",
    "РК",
    "РНФ",
    "РОБОАРТ",
    "Рожанский",
    "Роскомнадзор(а|)",
    "Росмолодёж(и|ь)",
    "Ростех",
    "Росэлектроника",
    "Росэнергоатом",
    "Росэнергоатома",
    "РС",
    "РТЛабс",
    "ру",
    "Рубинский",
    "Русал",
    "РЦНИТ",
    "РЭВ",
    "РЭС",
    "Ряполову",
    "Сhillbox",
    "сomedy",
    "Сorporation",
    "са",
    "Са",
    "Саважо",
    "Савостюка",
    "сай",
    "самолинзирующую",
    "Самолыгу",
    "Саруман(а|)",
    "Сбер(а|ом|)",
    "СБЧ",
    "сверхвысокоуровневых",
    "сверхкороткоимпульсной",
    "Светобитва",
    "Себиле",
    "Секлетовой",
    "Семенко",
    "Семенова",
    "СибАК",
    "Сибур",
    "СИБУР(а|е|)",
    "Сиверстали",
    "Сивковым",
    "Силардом",
    "Симовски",
    "Синемапарк",
    "Синецкая",
    "Синимекс",
    "Синте",
    "Системс",
    "скайп(е|)",
    "скалодроме",
    "СКЗИ",
    "СКИ",
    "Сколковский",
    "Сколковского",
    "Сколтех",
    "Сколтеха",
    "Скорлуханова",
    "СКТБ",
    "Смарт",
    "Смехнова",
    "Смусева",
    "СНИЛС",
    "сниффером",
    "СнК",
    "Собир",
    "Совкомбанк",
    "соосновател(ь|я)",
    "социалку",
    "СОШ",
    "спар",
    "СПбГУКиТ",
    "СПбГУТ",
    "СПбГЭТУ",
    "спекторометр",
    "спецводоочистки",
    "спецпоказов",
    "спецсвязь",
    "спинтроники",
    "сплэш",
    "СПО",
    "ССервО",
    "ССО",
    "ССУ",
    "ССУЗа",
    "Староверова",
    "стендап(а|)",
    "Стискал",
    "сториес",
    "Стоутон",
    "страйкбольное",
    "Стриклэнд",
    "стриминговых",
    "СТС",
    "стуДДень",
    "студзачёта",
    "Студзачёта",
    "Студотряд",
    "студотрядах",
    "студотряде",
    "СтудСовет",
    "СтудСовета",
    "студстарты",
    "Студстарты",
    "Стэл",
    "субнано",
    "субнаносекундных",
    "супербога",
    "сфоримируют",
    "СШП",
    "Сюше",
    "Сяоюн",
    "ТV",
    "Тарабриной",
    "Таранченко",
    "Татнефть",
    "Таулесс(а|)",
    "тахографии",
    "твитит",
    "Твиттер",
    "Теле2",
    "Тепломаркет",
    "Тепцова",
    "терагерцовым",
    "тераностики",
    "территориясмыслов",
    "Тетерюкова",
    "техзрения",
    "техлид(а|ы|)",
    "Технoлогическом",
    "технополи(е|с|се)",
    "Технопредпринимательство",
    "Технопредпринимательство",
    "техностартапы",
    "ТЗ",
    "тизер(ом|)",
    "тимлидов",
    "Тинькофф",
    "Тоехаси",
    "Точилов",
    "Траллеро",
    "Траньковым",
    "Требунских",
    "тревел",
    "тренажёрку",
    "трудоустройс",
    "ТРЦ",
    "ттн",
    "ТТН",
    "Тужикова",
    "ТулГУ",
    "Турищев",
    "Турклуб",
    "турклуба",
    "турнирщики",
    "турнирщиков",
    "Турьинские",
    "ТУСУР",
    "Угая",
    "удалёнка",
    "ужъ",
    "УМО",
    "универ(е|)",
    "УниверCity",
    "Уразов",
    "Усков(у|)",
    "Фаик",
    "факом",
    "факу",
    "Факультетус",
    "фаст",
    "ФГБОУ",
    "ФГНИИЦ",
    "ФГУ",
    "Фернандес",
    "ФИАН",
    "физф",
    "ФизФак",
    "ФизФака",
    "ФизФаке",
    "Физфакович",
    "ФизФаком",
    "ФизФакПознавательный",
    "ФизФаку",
    "фиксить",
    "Финк",
    "Финтеха",
    "финтехе",
    "ФиФа",
    "ФиФаФильм",
    "фич",
    "фичах",
    "фишинговые",
    "ФКН",
    "флаер",
    "флешмоб(е|)",
    "флюр(а|ой|у|ы)",
    "фм",
    "форумтаврида",
    "Фотоактив",
    "Фотовольтаика",
    "фотожанра",
    "фотозон(а|у)",
    "Фотоочет",
    "фотосепаратор(а|ов)",
    "фотофильтрами",
    "ФПК",
    "фреймворк(ам|ами|ах|е|и|)",
    "фрилансер",
    "фронтенд(а|)",
    "Фроня",
    "ФТИ",
    "ФТТ",
    "ФТТиН",
    "ФТТиНС",
    "ФТТНС",
    "фуд",
    "Фурдак",
    "ФФ",
    "ФЭКС",
    "ХII",
    "ХVIII",
    "хаба",
    "хакингу",
    "Халдейн",
    "Ханикаев",
    "Харкевич",
    "Хатунцев",
    "Хауз",
    "Хаула",
    "Хей",
    "хештег(ом|у|)",
    "химсдвигах",
    "ХимФаком",
    "Химфотопроект",
    "ХК",
    "Хмля",
    "хоккейно",
    "Хоккинг",
    "Холиной",
    "Холобаев",
    "Хользун",
    "Хользунах",
    "Хользунова",
    "хотфиксов",
    "ХХ",
    "хэштегом",
    "Цайтлер",
    "Целенаправление",
    "целеустремленн(ый|ым)",
    "целеустремленность",
    "Цзяотун",
    "ЦИПС",
    "цифровизации",
    "Цицилина",
    "ЦНИИ",
    "ЦФО",
    "ЦЧБ",
    "Цюрупы",
    "Часовских",
    "ЧБД",
    "Чевычелова",
    "Чер",
    "Черемизова",
    "Черепова",
    "черлидингу",
    "Чернавского",
    "Чернушкиной",
    "Черных",
    "Чеширский",
    "Чикунова",
    "чипирование",
    "чирлидинг(а|у)",
    "Чичков",
    "Чурюмова",
    "Шалапанова",
    "Шанхуи",
    "Шапеева",
    "Шарлотфест2017",
    "Шахрур",
    "Шварценгольт",
    "Шендрикова",
    "Шипчинский",
    "Шленцова",
    "Шметкова",
    "шников",
    "Шорин",
    "Шпот",
    "Шредингера",
    "Штрассман",
    "шумометра",
    "Шунина",
    "ЩедрыйВторник",
    "ый",
    "Эйдмана",
    "экзам",
    "Экотропы",
    "экотуризма",
    "ЭКОцентр",
    "экшн",
    "электрогазосварщик",
    "электроимульсионным",
    "электрокомпонентов",
    "Электросигнал",
    "Эльбрусиаде",
    "Энегельса",
    "Энерджиквантум",
    "эпидемиологически",
    "этог",
    "Эфко",
    "ЭФКО",
    "Югнефтепродукт",
    "ЮрФака",
    "ютуб",
    "Якубенко",
    "Яменской",
    "Яуров",
    "ЯФиТ",
    "Яхина",
    "Яхиной"
  ]
}
